README.md
setup.py
co6co.web_db.egg-info/PKG-INFO
co6co.web_db.egg-info/SOURCES.txt
co6co.web_db.egg-info/dependency_links.txt
co6co.web_db.egg-info/requires.txt
co6co.web_db.egg-info/top_level.txt
co6co.web_db.egg-info/zip-safe
co6co_web_db/__init__.py
co6co_web_db/utils.py
co6co_web_db/model/__init__.py
co6co_web_db/model/params/__init__.py
co6co_web_db/services/__init__.py
co6co_web_db/services/cacheManage.py
co6co_web_db/services/db_service.py
co6co_web_db/services/jwt_service.py
co6co_web_db/view_model/__init__.py