Metadata-Version: 2.2
Name: co6co.web_db
Version: 0.0.18
Summary: web db 扩展
Home-page: http://github.com/co6co
Author: co6co
Author-email: co6co@qq.com
Classifier: Programming Language :: Python :: 3
Classifier: Programming Language :: Python :: 3.6
Requires-Dist: co6co
Requires-Dist: co6co.web-session>=0.0.1
Requires-Dist: co6co.db-ext
Requires-Dist: co6co.sanic-ext>=0.0.9
Requires-Dist: multipart
Requires-Dist: sanic==23.6.0
Dynamic: author
Dynamic: author-email
Dynamic: classifier
Dynamic: description
Dynamic: description-content-type
Dynamic: home-page
Dynamic: requires-dist
Dynamic: summary
